mbuslite/__init__.py
mbuslite/bus.py
mbuslite/service.py
mbuslite-0.1.0.dist-info/METADATA
mbuslite-0.1.0.dist-info/WHEEL
mbuslite-0.1.0.dist-info/top_level.txt
mbuslite-0.1.0.dist-info/RECORD
