Metadata-Version: 2.1
Name: mbuslite
Version: 0.1.0
Summary: A small, in-process message bus implementation.
Home-page: https://gitlab.com/francisferrell/mbuslite
Author: Francis Ferrell
Author-email: francisferrell@gmail.com
License: MIT
Platform: UNKNOWN
Classifier: License :: OSI Approved :: MIT License
Classifier: Programming Language :: Python :: 3
Classifier: Programming Language :: Python :: 3.7
